vulkan_ilm/__init__.py
vulkan_ilm/benchmark.py
vulkan_ilm/cli.py
vulkan_ilm/config.py
vulkan_ilm/debug_amd.py
vulkan_ilm/installer.py
vulkan_ilm/llama.py
vulkan_ilm/models/__init__.py
vulkan_ilm/models/manager.py
vulkan_ilm/simple_llama.py
vulkan_ilm/streaming.py
vulkan_ilm/utils/__init__.py
vulkan_ilm/utils/subprocess_handler.py
vulkan_ilm/vulkan/detector.py
vulkan_ilm-0.1.1.dist-info/LICENSE
vulkan_ilm-0.1.1.dist-info/METADATA
vulkan_ilm-0.1.1.dist-info/WHEEL
vulkan_ilm-0.1.1.dist-info/entry_points.txt
vulkan_ilm-0.1.1.dist-info/RECORD
