Metadata-Version: 2.1
Name: vulkan-ilm
Version: 0.1.1
Summary: Pythonic LLM inference on legacy GPUs using Vulkan — GPU-accelerated local AI for AMD, Intel, and NVIDIA without CUDA.
Home-page: https://github.com/Talnz007/VulkanIlm
License: MIT
Keywords: vulkan,llm,local-ai,gpu,machine-learning,python,ai-inference,amd,intel,cuda-alternative,open-source
Author: Talha Niazi
Author-email: talhaniazai007@gmail.com
Requires-Python: >=3.9,<4.0
Classifier: Development Status :: 4 - Beta
Classifier: Intended Audience :: Developers
Classifier: License :: OSI Approved :: MIT License
Classifier: Operating System :: OS Independent
Classifier: Programming Language :: Python :: 3
Classifier: Programming Language :: Python :: 3.9
Classifier: Programming Language :: Python :: 3.10
Classifier: Programming Language :: Python :: 3.11
Classifier: Programming Language :: Python :: 3.12
Classifier: Programming Language :: Python :: 3.13
Classifier: Topic :: Scientific/Engineering :: Artificial Intelligence
Classifier: Topic :: Software Development :: Libraries
Requires-Dist: click (>=8.1.3,<9.0.0)
Requires-Dist: huggingface-hub (>=0.19.0,<0.20.0)
Requires-Dist: pyyaml (>=6.0,<7.0)
Requires-Dist: rich (>=13.4.2,<14.0.0)
Requires-Dist: tqdm (>=4.66.1,<5.0.0)
Project-URL: Bug Tracker, https://github.com/Talnz007/VulkanIlm/issues
Project-URL: Documentation, https://talnz007.github.io/VulkanIlm/#/
Project-URL: Docs, https://talnz007.github.io/VulkanIlm/#/
Project-URL: Repository, https://github.com/Talnz007/VulkanIlm
Project-URL: Wiki, https://github.com/Talnz007/VulkanIlm/wiki
